{"symbol": "HOLE","address": "0x03fB52D4eE633ab0D06C833E32EFdd8D388f3E6a","overview":{"en": "Super Black Hole is a deflationary cryptocurrency with 20% deflation burn rate. Every time HOLE is transacted 20% of the transaction is destroyed. Maximum supply was 2,500,000 tokens at the time of creation. This is a social experiment to see what happens with deflation on a bigger scale."},"email": "hello@superblackhole.com","website": "https://superblackhole.com/","state": "NORMAL","links": {"blog": "","twitter": "https://twitter.com/Superblackh0le","telegram": "https://t.me/superblackhole","github": ""}}