{
  "symbol": "YOO",
  "address": "0x1D4105534dA120DA243281cfC3f26Aaf038E2D6f",
  "overview":{
        "en": "Yooba is a decentralized e-commerce system based on blockchain technology, where anyone can securely and privately provide services and purchase services",
        "zh": "一个去中心化的，全球性的，安全的，隐私的，基于区块链的电子商务系统。致力于让所有消费者，安全、隐私、轻易的进行全球性的消费。"
  },
  "email": "yooba@yooba.org",
  "website": "https://yooba.org",
  "whitepaper": "https://yooba.org/assets/YoobaWhitePaper_en.pdf",
  "state": "NORMAL",
  "published_on": "2018-03-29",
  "initial_price":{
        "ETH":"0.000002857 ETH",
        "USD":"0.002 USD",
        "BTC":"0.0000002 BTC"
  },
  "links": {
    "blog": "https://blog.yooba.org",
    "twitter": "https://twitter.com/YoobaProject",
    "telegram": "https://t.me/yoobaproject",
    "github": "https://github.com/yooba-team",
    "facebook": "https://fb.me/YoobaProject",
    "reddit": "https://www.reddit.com/r/Yooba/"
  }
}
