{
  "symbol": "XDT",
  "address": "0x24222a2602b1d83483977c1eb2518e15e58eb907",
  "overview":{
        "en": "Credit the world",
        "zh": ""
  },
  "email": "info@detrust.io",
  "website": "https://detrust.io/",
  "published_on": "2018-05-25",
  "links": {
    "twitter": "https://twitter.com/Detrust_io",
    "telegram": "https://t.me/Detrust",
    "facebook": "https://www.facebook.com/Detruster/",
    "reddit": "https://www.reddit.com/user/Detrust_io/",
    "medium": "https://medium.com/@detrust"
  }
}
