{
    "symbol": "HFR",
    "address": "0x5fd138079490ad1b7eaa44a25ed04290d218a103",
    "overview": {
        "en": "Heat City is the castle which popularizes data and scientific thinking and spreads the intersection of science and culture to the acceptant who are interested in strategic frontier science and technology. Through blockchain technology, it is hoped that it will reach a higher level of consensus with a wider range of social institutes and higher-dimensional people so as to promote the commercialization and wider, deeper popularization of science and technology.",
        "zh": "热链之城是为给予对战略前沿科学技术感兴趣的受众，普及数据和科技思维，传播交叉科学文化的城堡。希望通过区块链技术，与更广泛的社会机构和更高维度的人群达成更高层级的共识，来推动科学技术的更广、更深的普及和科学技术的商业化！"
    },
    "email": "foundation@heatchain.org",
    "website": "http://heatchain.com/",
    "whitepaper": "http://heatchain.com/book/热链发展白皮书.pdf",
    "state": "NORMAL",
    "links": {
        "twitter": "https://twitter.com/heatchainHFR",
        "telegram": "https://t.me/HeatChainCn"
    }
}