{
    "symbol": "AET",
    "address": "0x93a6eFd1c4076b05526D6263aAFD91942f75e4A4",
    "overview": {
        "en": "AET is a universal encrypted digital rights certificate that any transactions and exhibitions in the art district can be guaranteed and supported by AET.",
        "zh": "AET 是通用加密数字权益证明在艺术区上的任何交易以及交易展现都可以通过AET来保障和支撑艺术品流通生态。"
    },
    "email": "artblock@yishu.com",
    "state": "LOCKED",
    "published_on": "2018-08-02",
    "initial_price": {
        "ETH": "0.0 ETH",
        "USD": "0.0 USD",
        "BTC": "0.0 BTC"
    },
    "links": {
        "telegram": "https://t.me/Art_Block"
    }
}